gpgodzilla.py
gpgodzilla-0.0.1.dist-info/LICENSE.txt
gpgodzilla-0.0.1.dist-info/METADATA
gpgodzilla-0.0.1.dist-info/WHEEL
gpgodzilla-0.0.1.dist-info/top_level.txt
gpgodzilla-0.0.1.dist-info/RECORD
