Metadata-Version: 2.1
Name: gpgodzilla
Version: 0.0.1
Summary: Modify large text file line by line and encrypt with GnuPG.
Home-page: https://github.com/yirzhou/gpgodzilla
Author: Yiren Zhou
Author-email: yiren.chow@gmail.com
License: UNKNOWN
Platform: UNKNOWN
Classifier: Programming Language :: Python :: 3
Classifier: Programming Language :: Python :: 3.6
Classifier: Programming Language :: Python :: 3.7
Classifier: Programming Language :: Python :: 3.8
Classifier: License :: OSI Approved :: Apache Software License
Classifier: Operating System :: MacOS
Classifier: Operating System :: POSIX
Classifier: Operating System :: POSIX :: Linux
